dask_ndfilters
